OpenSeesAPI/Database.py
OpenSeesAPI/Misc.py
OpenSeesAPI/OpenSees.py
OpenSeesAPI/Output.py
OpenSeesAPI/TCL.py
OpenSeesAPI/__init__.py
OpenSeesAPI/Analysis/Algorithm.py
OpenSeesAPI/Analysis/Analysis.py
OpenSeesAPI/Analysis/Analyze.py
OpenSeesAPI/Analysis/Constraints.py
OpenSeesAPI/Analysis/Eigen.py
OpenSeesAPI/Analysis/Integrator.py
OpenSeesAPI/Analysis/Numberer.py
OpenSeesAPI/Analysis/System.py
OpenSeesAPI/Analysis/Test.py
OpenSeesAPI/Analysis/__init__.py
OpenSeesAPI/Helpers/Materials.py
OpenSeesAPI/Helpers/Sections.py
OpenSeesAPI/Helpers/SolutionAlgorithms.py
OpenSeesAPI/Helpers/__init__.py
OpenSeesAPI/Model/BasicBuilder.py
OpenSeesAPI/Model/Constraint.py
OpenSeesAPI/Model/Node.py
OpenSeesAPI/Model/Pattern.py
OpenSeesAPI/Model/TimeSeries.py
OpenSeesAPI/Model/__init__.py
OpenSeesAPI/Model/Element/Element.py
OpenSeesAPI/Model/Element/GeomTransf.py
OpenSeesAPI/Model/Element/__init__.py
OpenSeesAPI/Model/Element/Material/NDMaterial.py
OpenSeesAPI/Model/Element/Material/Section.py
OpenSeesAPI/Model/Element/Material/UniaxialMaterial.py
OpenSeesAPI/Model/Element/Material/__init__.py
test/SampleScript1.py
test/SampleScript2.py
test/SampleScript3.py
test/SampleScript4.py
test/__init__.py
test/test.py
OpenSeesAPI-0.15.0.dist-info/METADATA
OpenSeesAPI-0.15.0.dist-info/WHEEL
OpenSeesAPI-0.15.0.dist-info/pbr.json
OpenSeesAPI-0.15.0.dist-info/top_level.txt
OpenSeesAPI-0.15.0.dist-info/RECORD
