Metadata-Version: 2.1
Name: OpenSeesAPI
Version: 0.15.0
Summary: A OpenSees Wrapper in Python
Home-page: http://github.com/nassermarafi/OpenSeesAPI
Author: Nasser Marafi
Author-email: marafi@uw.edu
License: MIT
Platform: UNKNOWN
